simsnn/__init__.py
simsnn/__main__.py
simsnn/core/__init__.py
simsnn/core/connections.py
simsnn/core/detectors.py
simsnn/core/networks.py
simsnn/core/nodes.py
simsnn/core/simulators.py
simsnn/examples/__init__.py
simsnn/examples/circuit.py
simsnn-1.0.2.dist-info/METADATA
simsnn-1.0.2.dist-info/WHEEL
simsnn-1.0.2.dist-info/licenses/LICENSE
simsnn-1.0.2.dist-info/RECORD
