Metadata-Version: 2.1
Name: simsnn
Version: 1.0.2
Summary: Radboud Spiking Neural Network Simulator
Project-URL: Homepage, https://gitlab.socsci.ru.nl/snnsimulator/simsnn
Project-URL: Bug Tracker, https://gitlab.socsci.ru.nl/snnsimulator/simsnn/-/issues
Author-email: Arne Diehl <arne.diehl@donders.ru.nl>
License-File: LICENSE
Classifier: License :: OSI Approved :: MIT License
Classifier: Operating System :: OS Independent
Classifier: Programming Language :: Python :: 3
Requires-Python: >=3.7
